wildcat/__init__.py
wildcat/annealer/__init__.py
wildcat/annealer/base_annealer.py
wildcat/annealer/simulated/__init__.py
wildcat/annealer/simulated/base_simulated_annealing_strategy.py
wildcat/annealer/simulated/simulated_annealer.py
wildcat/annealer/simulated/single_spin_flip_strategy.py
wildcat/annealer/simulated/temperature_schedule.py
wildcat/network/__init__.py
wildcat/network/endpoint.py
wildcat/network/local_endpoint.py
wildcat/solver/__init__.py
wildcat/solver/base_solver.py
wildcat/solver/ising_hamiltonian_solver.py
wildcat/solver/qubo_solver.py
wildcat/solver/trading_trajectory_solver.py
wildcat/solver/tsp_solver.py
wildcat/util/__init__.py
wildcat/util/json_encoder.py
wildcat/util/matrix.py
wildcat-0.0.13.dist-info/METADATA
wildcat-0.0.13.dist-info/RECORD
wildcat-0.0.13.dist-info/WHEEL
wildcat-0.0.13.dist-info/top_level.txt
