Metadata-Version: 2.1
Name: wildcat
Version: 0.0.13
Summary: Wildcat Python SDK to Use Annealers
Home-page: https://github.com/mdrft/wildcat
Author: Shumpei Kobayashi
Author-email: skonb@w-ax.is
License: MIT
Download-URL: https://github.com/mdrft/wildcat_qdk/tarball/0.0.13
Platform: UNKNOWN
Classifier: Development Status :: 3 - Alpha
Classifier: Intended Audience :: Developers
Classifier: Programming Language :: Python :: 3
Requires-Dist: numpy
Requires-Dist: requests-futures
Requires-Dist: matplotlib
